voca/__init__.py
voca/__main__.py
voca/app.py
voca/caster_adapter.py
voca/cli.py
voca/config.py
voca/context.py
voca/listen.py
voca/log.py
voca/manager.py
voca/mic.py
voca/parsing.py
voca/patching.py
voca/platforms.py
voca/pronunciation.toml
voca/streaming.py
voca/utils.py
voca/worker.py
voca/plugins/__init__.py
voca/plugins/basic.py
voca/plugins/math.py
voca/plugins/no.py
voca/plugins/python.py
voca/plugins/stopstart.py
voca/plugins/terminator.py
voca/plugins/turtle_context.py
voca/plugins/vscode.py
voca/plugins/yes.py
voca-0.1.10.dist-info/AUTHORS.rst
voca-0.1.10.dist-info/LICENSE
voca-0.1.10.dist-info/METADATA
voca-0.1.10.dist-info/WHEEL
voca-0.1.10.dist-info/entry_points.txt
voca-0.1.10.dist-info/top_level.txt
voca-0.1.10.dist-info/RECORD
