Metadata-Version: 2.1
Name: voca
Version: 0.1.10
Summary: Control your computer by voice!
Home-page: https://github.com/python-voca/voca
Author: Full Name
Author-email: email@example.com
License: UNKNOWN
Platform: UNKNOWN
Classifier: License :: OSI Approved :: GNU General Public License v3 (GPLv3)
Classifier: Development Status :: 3 - Alpha
Classifier: Intended Audience :: Developers
Classifier: Operating System :: Unix
Classifier: Operating System :: POSIX
Classifier: Operating System :: Microsoft :: Windows
Classifier: Programming Language :: Python
Classifier: Programming Language :: Python :: 3.6
Classifier: Programming Language :: Python :: 3.7
Classifier: Programming Language :: Python :: Implementation :: CPython
Classifier: Programming Language :: Python :: Implementation :: PyPy
Classifier: Topic :: Utilities
Requires-Python: >=3.6
Requires-Dist: ws4py
Requires-Dist: pyaudio
Requires-Dist: click
Requires-Dist: trio
Requires-Dist: toml
Requires-Dist: importlib-resources
Requires-Dist: six
Requires-Dist: sympy
Requires-Dist: pyautogui
Requires-Dist: pynput
Requires-Dist: dragonfly2
Requires-Dist: atpublic
Requires-Dist: eliot-tree
